{
  "pack_id": "default",
  "pack_identity": "local:rumi/default-pack",
  "version": "1.0.0",
  "vocabulary": {
    "types": [
      "chats",
      "settings",
      "shared",
      "storage",
      "foundation",
      "io",
      "service"
    ]
  },
  "metadata": {
    "name": "Rumi AI Default Pack",
    "description": "Rumi AI OSの基本コンポーネントセット。チャット管理、設定、HTTP API、ファイル管理などの基盤機能を提供します。",
    "author": "Rumi AI Team",
    "license": "MIT",
    "homepage": "",
    "repository": ""
  },
  "dependencies": {},
  "components": {
    "chats:chats_v1": {
      "type": "chats",
      "id": "chats_v1",
      "path": "components/chats"
    },
    "settings:settings_v1": {
      "type": "settings",
      "id": "settings_v1",
      "path": "components/settings"
    },
    "shared:shared_v1": {
      "type": "shared",
      "id": "shared_v1",
      "path": "components/shared"
    },
    "storage:storage_v1": {
      "type": "storage",
      "id": "storage_v1",
      "path": "components/storage"
    },
    "foundation:foundation_v1": {
      "type": "foundation",
      "id": "foundation_v1",
      "path": "components/foundation"
    },
    "io:io_http_api_v1": {
      "type": "io",
      "id": "io_http_api_v1",
      "path": "components/io"
    },
    "service:services_message_stub_v1": {
      "type": "service",
      "id": "services_message_stub_v1",
      "path": "components/services/message_stub"
    }
  },
  "load_order": [
    "shared:shared_v1",
    "foundation:foundation_v1",
    "chats:chats_v1",
    "settings:settings_v1",
    "storage:storage_v1",
    "service:services_message_stub_v1",
    "io:io_http_api_v1"
  ]
}